{
	"actorSpecification": 1,
	"fields": {
		"type": {
			"type": "string"
		},
		"targetUsername": {
			"type": "string"
		},
		"resolvedUsername": {
			"type": "string"
		},
		"commentOwnerUsername": {
			"type": "string"
		},
		"commentKind": {
			"type": "string"
		},
		"replyDepth": {
			"type": "number"
		},
		"parentCommentPermalink": {
			"type": ["string", "null"]
		},
		"commentText": {
			"type": "string"
		},
		"createdAt": {
			"type": ["string", "null"],
			"format": "date-time"
		},
		"createdAtLabel": {
			"type": ["string", "null"]
		},
		"commentPermalink": {
			"type": "string"
		},
		"postUrl": {
			"type": "string"
		},
		"postShortcode": {
			"type": "string"
		},
		"postOwnerUsername": {
			"type": "string"
		},
		"sourceSurface": {
			"type": "string"
		},
		"sourceUrl": {
			"type": "string"
		},
		"discoverySource": {
			"type": "string"
		},
		"discoveredViaUsername": {
			"type": ["string", "null"]
		},
		"matchConfidence": {
			"type": "string"
		},
		"matchReason": {
			"type": "string"
		}
	},
	"views": {
		"overview": {
			"title": "Matched comments",
			"transformation": {
				"fields": [
					"createdAt",
					"targetUsername",
					"commentOwnerUsername",
					"commentKind",
					"replyDepth",
					"commentText",
					"commentPermalink",
					"parentCommentPermalink",
					"postUrl",
					"postOwnerUsername",
					"discoverySource",
					"discoveredViaUsername",
					"matchConfidence"
				],
				"desc": true
			},
			"display": {
				"component": "table",
				"properties": {
					"createdAt": {
						"label": "Created at",
						"format": "date"
					},
					"targetUsername": {
						"label": "Target"
					},
					"commentOwnerUsername": {
						"label": "Comment owner"
					},
					"commentKind": {
						"label": "Kind"
					},
					"replyDepth": {
						"label": "Reply depth",
						"format": "number"
					},
					"commentText": {
						"label": "Comment text"
					},
					"commentPermalink": {
						"label": "Comment permalink",
						"format": "link"
					},
					"parentCommentPermalink": {
						"label": "Parent comment",
						"format": "link"
					},
					"postUrl": {
						"label": "Post",
						"format": "link"
					},
					"postOwnerUsername": {
						"label": "Post owner"
					},
					"discoverySource": {
						"label": "Discovery source"
					},
					"discoveredViaUsername": {
						"label": "Discovered via"
					},
					"matchConfidence": {
						"label": "Confidence"
					}
				}
			}
		}
	}
}
